new_try/my_array.vhd
library ieee;
use ieee.std_logic_1164.all;
use IEEE.numeric_std.all;

entity my_array is
  generic (
    ROWS : integer := 4; -- number of rows in the array
    COLS : integer := 4 -- number of columns in the array
  );
  port (
    clk : in std_logic;
    rst : in std_logic;
    row_idx : in std_logic_vector(ROWS - 1 downto 0);
    col_idx : in std_logic_vector(COLS - 1 downto 0);
    data_out : out std_logic
  );
end my_array;

architecture behavioral of my_array is
  type array_type is array(0 to ROWS - 1, 0 to COLS - 1) of std_logic;
  signal array2d : array_type := (
  ('1', '0', '1', '0'),
    ('0', '1', '0', '1'),
    ('1', '0', '1', '0'),
    ('0', '1', '0', '1')
  );
begin
  process (clk)
  begin
    if rising_edge(clk) then
      if rst = '0' then
        data_out <= '0';
      else
        data_out <= array2d(to_integer(unsigned(row_idx)), to_integer(unsigned(col_idx)));
      end if;
    end if;
  end process;
end behavioral;

new_try/my_array_tb.vhd
library ieee;
use ieee.std_logic_1164.all;
use ieee.numeric_std.all;

entity my_array_tb is
end my_array_tb;

architecture behavioral of my_array_tb is
  constant ROWS : integer := 4;
  constant COLS : integer := 4;

  signal clk : std_logic := '0';
  signal rst : std_logic := '0';
  signal row_idx : std_logic_vector(ROWS - 1 downto 0);
  signal col_idx : std_logic_vector(COLS - 1 downto 0);
  signal data_out : std_logic;

  component my_array
    generic (
      ROWS : integer := 4;
      COLS : integer := 4
    );
    port (
      clk : in std_logic;
      rst : in std_logic;
      row_idx : in std_logic_vector(ROWS - 1 downto 0);
      col_idx : in std_logic_vector(COLS - 1 downto 0);
      data_out : out std_logic
    );
  end component;

begin

  dut : my_array
  generic map(
    ROWS => ROWS,
    COLS => COLS
  )
  port map(
    clk => clk,
    rst => rst,
    row_idx => row_idx,
    col_idx => col_idx,
    data_out => data_out
  );

  -- Clock generation process
  clk_gen : process
  begin
    while now < 1000 ns loop
      clk <= '0';
      wait for 10 ns;
      clk <= '1';
      wait for 10 ns;
    end loop;
    wait;
  end process clk_gen;

  -- Reset process
  rst_proc : process
  begin
    rst <= '1';
    wait for 10 ns;
    rst <= '0';
    wait for 10 ns;
    rst <= '1';
    wait;
  end process rst_proc;

  -- Test process
  test_proc : process
  begin
    -- Test each element of the array
    for i in 0 to ROWS - 1 loop
      for j in 0 to COLS - 1 loop
        row_idx <= std_logic_vector(to_unsigned(i, row_idx'length));
        col_idx <= std_logic_vector(to_unsigned(j, col_idx'length));
        wait for 10 ns;
        --assert to_bit(data_out) = to_bit(((i + j) mod 2)) report "Unexpected value at (" & integer'image(i) & ", " & integer'image(j) & ")" severity error;
      end loop;
    end loop;

    -- Test out-of-bounds indices
    --row_idx <= ROWS;
    --col_idx <= COLS;
    wait for 10 ns;
    --assert to_bit(data_out) = '0' report "Unexpected value at out-of-bounds index" severity error;

    wait;
  end process test_proc;

end behavioral;

new_try/my_array.vcd
$date
  Fri Mar 17 17:48:49 2023
$end
$version
  GHDL v0
$end
$timescale
  1 fs
$end
$scope module standard $end
$upscope $end
$scope module std_logic_1164 $end
$upscope $end
$scope module numeric_std $end
$upscope $end
$scope module my_array_tb $end
$var reg 1 ! clk $end
$var reg 1 " rst $end
$var reg 4 # row_idx[3:0] $end
$var reg 4 $ col_idx[3:0] $end
$var reg 1 % data_out $end
$scope module dut $end
$var reg 1 & clk $end
$var reg 1 ' rst $end
$var reg 4 ( row_idx[3:0] $end
$var reg 4 ) col_idx[3:0] $end
$var reg 1 * data_out $end
$comment array2d is not handled $end
$upscope $end
$upscope $end
$enddefinitions $end
#0
0!
1"
b0000 #
b0000 $
U%
0&
1'
b0000 (
b0000 )
U*
#10000000
1!
0"
b0001 $
0%
1&
0'
b0001 )
0*
#20000000
0!
1"
b0010 $
0&
1'
b0010 )
#30000000
1!
b0011 $
1&
b0011 )
#40000000
0!
b0001 #
b0000 $
0&
b0001 (
b0000 )
#50000000
1!
b0001 $
1%
1&
b0001 )
1*
#60000000
0!
b0010 $
0&
b0010 )
#70000000
1!
b0011 $
1&
b0011 )
#80000000
0!
b0010 #
b0000 $
0&
b0010 (
b0000 )
#90000000
1!
b0001 $
0%
1&
b0001 )
0*
#100000000
0!
b0010 $
0&
b0010 )
#110000000
1!
b0011 $
1&
b0011 )
#120000000
0!
b0011 #
b0000 $
0&
b0011 (
b0000 )
#130000000
1!
b0001 $
1%
1&
b0001 )
1*
#140000000
0!
b0010 $
0&
b0010 )
#150000000
1!
b0011 $
1&
b0011 )
